sphinxcontrib_dashbuilder-0.1.0-py3.3-nspkg.pth
sphinxcontrib/dashbuilder/builder.py
sphinxcontrib/dashbuilder/writer.py
sphinxcontrib/dashbuilder/__init__.py
sphinxcontrib_dashbuilder-0.1.0.dist-info/DESCRIPTION.rst
sphinxcontrib_dashbuilder-0.1.0.dist-info/METADATA
sphinxcontrib_dashbuilder-0.1.0.dist-info/metadata.json
sphinxcontrib_dashbuilder-0.1.0.dist-info/namespace_packages.txt
sphinxcontrib_dashbuilder-0.1.0.dist-info/RECORD
sphinxcontrib_dashbuilder-0.1.0.dist-info/top_level.txt
sphinxcontrib_dashbuilder-0.1.0.dist-info/WHEEL
