Metadata-Version: 2.0
Name: sphinxcontrib-dashbuilder
Version: 0.1.0
Summary: Sphinx builder extension to generate a 'Documentation Set' for `dash API browser`.
Home-page: http://bitbucket.org/shimizukawa/sphinxcontrib_dashbuilder
Author: shimizukawa
Author-email: shimizukawa@gmail.com
License: BSD
Download-URL: http://pypi.python.org/pypi/sphinxcontrib-dashbuilder
Platform: any
Classifier: Development Status :: 4 - Beta
Classifier: Environment :: Console
Classifier: Environment :: Web Environment
Classifier: Intended Audience :: Developers
Classifier: License :: OSI Approved :: BSD License
Classifier: Operating System :: OS Independent
Classifier: Programming Language :: Python
Classifier: Programming Language :: Python
Classifier: Programming Language :: Python :: 2
Classifier: Programming Language :: Python :: 2.6
Classifier: Programming Language :: Python :: 2.7
Classifier: Programming Language :: Python :: 3
Classifier: Programming Language :: Python :: 3.3
Classifier: Programming Language :: Python :: 3.4
Classifier: Topic :: Documentation
Classifier: Topic :: Utilities
Requires-Dist: Sphinx (>=1.2)
Requires-Dist: six
Provides-Extra: test
Requires-Dist: nose2; extra == 'test'
